[
    {
        "node_type": "keyword_extraction",
        "keywords": [
            "races",
            "year",
            "2010",
            "grand prixs",
            "outside",
            "Asia",
            "Europe",
            "How many",
            "held"
        ],
        "status": "success"
    },
    {
        "node_type": "entity_retrieval",
        "similar_columns": {
            "races": [
                "year"
            ]
        },
        "similar_values": {
            "races": {
                "name": [
                    "Dutch Grand Prix"
                ]
            },
            "circuits": {
                "country": [
                    "Malaysia"
                ]
            }
        },
        "status": "success"
    },
    {
        "node_type": "context_retrieval",
        "schema_with_descriptions": {
            "driverstandings": {
                "points": {
                    "column_name": "",
                    "column_description": "how many points acquired in each race",
                    "value_description": ""
                },
                "raceid": {
                    "column_name": "constructor Reference name",
                    "column_description": "id number identifying which races",
                    "value_description": ""
                },
                "wins": {
                    "column_name": "",
                    "column_description": "wins",
                    "value_description": ""
                }
            },
            "constructorstandings": {
                "points": {
                    "column_name": "",
                    "column_description": "how many points acquired in each race",
                    "value_description": ""
                },
                "raceid": {
                    "column_name": "race id",
                    "column_description": "id number identifying which races",
                    "value_description": ""
                }
            },
            "qualifying": {
                "q2": {
                    "column_name": "qualifying 2",
                    "column_description": "time in qualifying 2",
                    "value_description": "in minutes / seconds / ...    only top 15 in the q1 has the record of q2  Q2 is slightly shorter but follows the same format. Drivers try to put down their best times to move on to Q1 as one of the 10 fastest cars. The five outside of the top 10 are eliminated and start the race from 11th to 15th based on their best lap time."
                },
                "number": {
                    "column_name": "",
                    "column_description": "number",
                    "value_description": ""
                },
                "qualifyid": {
                    "column_name": "qualify Id",
                    "column_description": "the unique identification number identifying qualifying",
                    "value_description": "How does F1 Sprint qualifying work? Sprint qualifying is essentially a short-form Grand Prix \u2013 a race that is one-third the number of laps of the main event on Sunday. However, the drivers are battling for positions on the grid for the start of Sunday's race."
                },
                "q3": {
                    "column_name": "qualifying 3",
                    "column_description": "time in qualifying 3",
                    "value_description": "in minutes / seconds / ...    only top 10 in the q2 has the record of q3"
                },
                "q1": {
                    "column_name": "qualifying 1",
                    "column_description": "time in qualifying 1",
                    "value_description": "in minutes / seconds / ...    Q1 lap times determine pole position and the order of the front 10 positions on the grid. The slowest driver in Q1 starts 10th, the next starts ninth and so on.  All 20 F1 drivers participate in the first period, called Q1, with each trying to set the fastest time possible. Those in the top 15 move on to the next period of qualifying, called Q2. The five slowest drivers are eliminated and will start the race in the last five positions on the grid."
                }
            },
            "races": {
                "url": {
                    "column_name": "",
                    "column_description": "introduction of races",
                    "value_description": ""
                },
                "name": {
                    "column_name": "",
                    "column_description": "name of the race",
                    "value_description": ""
                },
                "year": {
                    "column_name": "",
                    "column_description": "year",
                    "value_description": ""
                },
                "time": {
                    "column_name": "",
                    "column_description": "time of the location",
                    "value_description": ""
                }
            },
            "pitstops": {
                "raceid": {
                    "column_name": "race ID",
                    "column_description": "the identification number identifying race",
                    "value_description": ""
                }
            },
            "results": {
                "raceid": {
                    "column_name": "race ID",
                    "column_description": "the identification number identifying the race",
                    "value_description": ""
                },
                "number": {
                    "column_name": "",
                    "column_description": "number",
                    "value_description": ""
                }
            },
            "laptimes": {
                "raceid": {
                    "column_name": "race ID",
                    "column_description": "the identification number identifying race",
                    "value_description": ""
                }
            },
            "drivers": {
                "dob": {
                    "column_name": "date of birth",
                    "column_description": "date of birth",
                    "value_description": ""
                },
                "number": {
                    "column_name": "",
                    "column_description": "number",
                    "value_description": ""
                }
            },
            "circuits": {
                "lat": {
                    "column_name": "latitude",
                    "column_description": "latitude of location of circuit",
                    "value_description": ""
                },
                "lng": {
                    "column_name": "longitude",
                    "column_description": "longitude of location of circuit",
                    "value_description": "Location coordinates: (lat, lng)"
                },
                "country": {
                    "column_name": "",
                    "column_description": "country of circuit",
                    "value_description": ""
                }
            },
            "constructorresults": {
                "status": {
                    "column_name": "",
                    "column_description": "status",
                    "value_description": ""
                }
            }
        },
        "status": "success"
    },
    {
        "node_type": "column_filtering",
        "tentative_schema": {
            "circuits": [
                "name",
                "location",
                "country",
                "lng",
                "circuitId"
            ],
            "constructors": [
                "constructorId"
            ],
            "drivers": [
                "driverId"
            ],
            "seasons": [
                "year"
            ],
            "races": [
                "raceId",
                "year",
                "name",
                "circuitId"
            ],
            "constructorResults": [
                "raceId",
                "constructorResultsId",
                "constructorId"
            ],
            "constructorStandings": [
                "constructorStandingsId",
                "raceId",
                "constructorId"
            ],
            "driverStandings": [
                "driverStandingsId",
                "raceId",
                "driverId"
            ],
            "lapTimes": [
                "raceId",
                "driverId",
                "lap"
            ],
            "pitStops": [
                "raceId",
                "driverId",
                "stop"
            ],
            "qualifying": [
                "qualifyId",
                "raceId",
                "driverId",
                "constructorId"
            ],
            "status": [
                "statusId"
            ],
            "results": [
                "resultId",
                "raceId",
                "driverId",
                "constructorId",
                "statusId"
            ]
        },
        "missing_table_status": "success",
        "missing_tables": [],
        "missing_column_status": "success",
        "missing_columns": [],
        "correct_columns": {
            "races": [
                "raceid",
                "circuitid",
                "year"
            ],
            "circuits": [
                "circuitid",
                "country"
            ]
        },
        "status": "success"
    },
    {
        "node_type": "table_selection",
        "tentative_schema": {
            "circuits": [
                "name",
                "location",
                "country",
                "lng",
                "circuitId"
            ],
            "races": [
                "raceId",
                "year",
                "name",
                "circuitId"
            ],
            "seasons": [
                "year"
            ]
        },
        "chain_of_thought_reasoning": "The question asks for the number of races held in 2010 outside Asia and Europe. The hint suggests focusing on grand prix, which implies we need to consider the 'circuits' table. The 'races' table is also necessary as it links to the 'circuits' table and provides the year information. The 'seasons' table is required to filter the races by year 2010. Finally, the 'status' table is not necessary for this question, as it only provides information about the race status, not the location.",
        "selected_tables": [
            "circuits",
            "races",
            "seasons"
        ],
        "missing_table_status": "success",
        "missing_tables": [],
        "missing_column_status": "success",
        "missing_columns": [],
        "correct_columns": {
            "races": [
                "raceid",
                "circuitid",
                "year"
            ],
            "circuits": [
                "circuitid",
                "country"
            ]
        },
        "status": "success"
    },
    {
        "node_type": "column_selection",
        "tentative_schema": {
            "circuits": [
                "circuitId",
                "country"
            ],
            "races": [
                "circuitId",
                "year",
                "name"
            ]
        },
        "model_selected_columns": {
            "circuits": [
                "circuitId",
                "country"
            ],
            "races": [
                "circuitId",
                "year",
                "name"
            ]
        },
        "chain_of_thought_reasoning": "The question asks for races in 2010 held outside Asia and Europe. The hint points to the country column in the circuits table, which has examples like 'Malaysia' for Asia. We need to filter races by circuit location, so we need the circuitId and country columns. We also need the year column from the races table to filter by 2010. Finally, we need the name column from the races table to get the race names.",
        "missing_table_status": "success",
        "missing_tables": [],
        "missing_column_status": "missing_column",
        "missing_columns": [
            "'races'.'raceid'"
        ],
        "correct_columns": {
            "races": [
                "raceid",
                "circuitid",
                "year"
            ],
            "circuits": [
                "circuitid",
                "country"
            ]
        },
        "status": "success"
    },
    {
        "node_type": "candidate_generation",
        "SQL": "SELECT COUNT(T2.name) FROM circuits AS T1 INNER JOIN races AS T2 ON T1.circuitId = T2.circuitId WHERE T2.year = 2010 AND T2.name = 'Dutch Grand Prix' AND T1.country NOT IN ('Malaysia') ",
        "status": "success"
    },
    {
        "node_type": "revision",
        "chain_of_thought_reasoning": "I started by identifying the tables and columns related to the question. The question asks for the number of races held outside Asia and Europe in the year 2010. I noticed that the 'circuits' table has a 'country' column that can be used to filter out races held in Asia and Europe. I then joined the 'circuits' table with the 'races' table using the 'circuitId' column. I filtered the results to only include races held in the year 2010 and used the 'name' column to filter out races held in Asia and Europe. Finally, I used the COUNT function to count the number of races that meet the conditions.",
        "SQL": "SELECT COUNT(*) FROM circuits AS T1 INNER JOIN races AS T2 ON T1.circuitId = T2.circuitId WHERE T2.year = 2010 AND T1.country NOT IN ('Malaysia', 'Europe') AND T2.name NOT LIKE '%Asian Grand Prix%'",
        "status": "success"
    },
    {
        "node_type": "evaluation",
        "candidate_generation": {
            "exec_res": 0,
            "exec_err": "incorrect answer",
            "Question": "How many races in the year 2010 are held on grand prixs outside Asia and Europe?",
            "Evidence": "",
            "GOLD_SQL": "SELECT COUNT(T3.raceId) FROM circuits AS T1 INNER JOIN races AS T3 ON T3.circuitID = T1.circuitId WHERE T1.country NOT IN ( 'Bahrain', 'China', 'Singapore', 'Japan', 'Korea', 'Turkey', 'UAE', 'Malaysia', 'Spain', 'Monaco', 'Azerbaijan', 'Austria', 'Belgium', 'France', 'Germany', 'Hungary', 'Italy', 'UK' ) AND T3.year = 2010",
            "PREDICTED_SQL": "SELECT COUNT(T2.name) FROM circuits AS T1 INNER JOIN races AS T2 ON T1.circuitId = T2.circuitId WHERE T2.year = 2010 AND T2.name = 'Dutch Grand Prix' AND T1.country NOT IN ('Malaysia') "
        },
        "revision": {
            "exec_res": 0,
            "exec_err": "incorrect answer",
            "Question": "How many races in the year 2010 are held on grand prixs outside Asia and Europe?",
            "Evidence": "",
            "GOLD_SQL": "SELECT COUNT(T3.raceId) FROM circuits AS T1 INNER JOIN races AS T3 ON T3.circuitID = T1.circuitId WHERE T1.country NOT IN ( 'Bahrain', 'China', 'Singapore', 'Japan', 'Korea', 'Turkey', 'UAE', 'Malaysia', 'Spain', 'Monaco', 'Azerbaijan', 'Austria', 'Belgium', 'France', 'Germany', 'Hungary', 'Italy', 'UK' ) AND T3.year = 2010",
            "PREDICTED_SQL": "SELECT COUNT(*) FROM circuits AS T1 INNER JOIN races AS T2 ON T1.circuitId = T2.circuitId WHERE T2.year = 2010 AND T1.country NOT IN ('Malaysia', 'Europe') AND T2.name NOT LIKE '%Asian Grand Prix%'"
        },
        "status": "success"
    }
]